macos_eye_care_plan/__init__.py
macos_eye_care_plan/main.py
macos_eye_care_plan/prompts.py
macos_eye_care_plan-2025.12.21131932.dist-info/METADATA
macos_eye_care_plan-2025.12.21131932.dist-info/WHEEL
macos_eye_care_plan-2025.12.21131932.dist-info/top_level.txt
macos_eye_care_plan-2025.12.21131932.dist-info/RECORD
