Metadata-Version: 2.4
Name: macos-eye-care-plan
Version: 2025.12.21131932
Summary: A new package designed to help users maintain healthy eye habits while using macOS devices. The package takes user input describing their daily screen usage patterns, work environment, and any existin
Author-email: macos-eye-care-plan <hi@eugene.plus>
License: MIT
Project-URL: Homepage, https://github.com/chigwell/macos-eye-care-plan
Requires-Python: >=3.9
Requires-Dist: langchain-llm7>=0.0.0
Requires-Dist: llmatch-messages>=0.0.0
Requires-Dist: langchain-core>=0.3.0
